llama_api_server/__init__.py
llama_api_server/__main__.py
llama_api_server/app.py
llama_api_server/chat_engine.py
llama_api_server/config.py
llama_api_server/model_pool.py
llama_api_server/utils.py
llama_api_server/models/llama_cpp.py
llama_api_server/models/pyllama.py
llama_api_server/models/pyllama_quant.py
llama_api_server-0.3.4.dist-info/METADATA
llama_api_server-0.3.4.dist-info/WHEEL
llama_api_server-0.3.4.dist-info/licenses/LICENSE
llama_api_server-0.3.4.dist-info/RECORD
