Metadata-Version: 2.1
Name: llama_api_server
Version: 0.3.4
Summary: A OpenAI API compatible REST server for llama.
Project-URL: homepage, https://github.com/iaalm/llama-api-server
Project-URL: repository, https://github.com/iaalm/llama-api-server
Author-email: iaalm <iaalmsimon@gmail.com>
License: MIT
License-File: LICENSE
Classifier: Development Status :: 3 - Alpha
Classifier: License :: OSI Approved :: MIT License
Classifier: Programming Language :: Python :: 3 :: Only
Classifier: Programming Language :: Python :: 3.9
Classifier: Programming Language :: Python :: 3.10
Classifier: Programming Language :: Python :: 3.11
Requires-Python: >=3.9
Requires-Dist: flask>=2.0.0
Requires-Dist: llamacpp>=0.1.11
Requires-Dist: numpy
Requires-Dist: pyyaml
Provides-Extra: pyllama
Requires-Dist: gptq; extra == 'pyllama'
Requires-Dist: pyllama>=0.0.9; extra == 'pyllama'
Requires-Dist: transformers>=4.27.4; extra == 'pyllama'
